{
  "game_type": "escape_game",
  "schema_version": "1.0",
  "title": "Mini-Escape-Room – Cloud Service-Modelle (AP1)",
  "topic": "IaaS • PaaS • SaaS (Verantwortung, Kontrolle, Beispiele)",
  "estimated_minutes": 15,
  "sections": [
    {
      "id": "service-modelle-sort",
      "type": "sort",
      "title": "Rätsel 1: IaaS / PaaS / SaaS zuordnen",
      "subtitle": "Ordne Beschreibungen dem richtigen Cloud-Modell zu.",
      "hintDefault": "IaaS: du betreibst OS/App. PaaS: Plattform ist da, du lieferst Code. SaaS: fertige App nutzen.",
      "sortColumns": [
        { "zone": "iaas", "label": "IaaS", "hint": "(VMs/Storage/Netzwerk, Kunde verwaltet OS/App)" },
        { "zone": "paas", "label": "PaaS", "hint": "(Runtime/DB, weniger Betrieb/Kontrolle)" },
        { "zone": "saas", "label": "SaaS", "hint": "(fertige Anwendung, schnell startklar)" }
      ],
      "sortCards": [
        { "id": "m1", "text": "Virtuelle Maschinen, Storage und Netzwerk mieten", "correctZone": "iaas" },
        { "id": "m2", "text": "Kunde installiert/patcht Betriebssystem und betreibt die App selbst", "correctZone": "iaas" },
        { "id": "m3", "text": "Plattform liefert Runtime; du deployest Code", "correctZone": "paas" },
        { "id": "m4", "text": "Managed Datenbank/Runtime – weniger Admin-Aufwand", "correctZone": "paas" },
        { "id": "m5", "text": "Fertige Anwendung im Browser nutzen", "correctZone": "saas" },
        { "id": "m6", "text": "Schnell startklar, geringste Kontrolle über Betrieb/Plattform", "correctZone": "saas" }
      ]
    },
    {
      "id": "verantwortung-quiz",
      "type": "quiz",
      "title": "Rätsel 2: Kontrolle & Verantwortung (AP1)",
      "subtitle": "Wer verwaltet was?",
      "hintDefault": "Mehr Kontrolle = mehr Betriebspflichten. Weniger Kontrolle = schneller, aber weniger anpassbar.",
      "questions": [
        {
          "id": "q1",
          "text": "1. Bei welchem Modell verwaltet der Kunde typischerweise Betriebssystem und eigene Anwendungen selbst?",
          "options": [
            { "value": "a", "text": "SaaS" },
            { "value": "b", "text": "PaaS" },
            { "value": "c", "text": "IaaS" }
          ],
          "correct": "c"
        },
        {
          "id": "q2",
          "text": "2. Welches Modell liefert typischerweise Runtime/DB als Plattform, reduziert Betrieb, aber nimmt Kontrolle?",
          "options": [
            { "value": "a", "text": "PaaS" },
            { "value": "b", "text": "IaaS" },
            { "value": "c", "text": "SaaS" }
          ],
          "correct": "a"
        },
        {
          "id": "q3",
          "text": "3. Bei welchem Modell ist man am schnellsten produktiv, hat aber die geringste Kontrolle über die technische Umsetzung?",
          "options": [
            { "value": "a", "text": "IaaS" },
            { "value": "b", "text": "PaaS" },
            { "value": "c", "text": "SaaS" }
          ],
          "correct": "c"
        }
      ]
    },
    {
      "id": "praxis-faelle-sort",
      "type": "sort",
      "title": "Finale: Praxisfälle – welches Modell passt?",
      "subtitle": "Wähle das Modell, das am ehesten passt.",
      "hintDefault": "IaaS für maximale Kontrolle/Custom-Betrieb. PaaS für „Code liefern, Plattform nutzen“. SaaS für fertige Lösung.",
      "sortColumns": [
        { "zone": "iaas", "label": "IaaS", "hint": "(max. Kontrolle, eigener Betrieb)" },
        { "zone": "paas", "label": "PaaS", "hint": "(weniger Betrieb, Code deployen)" },
        { "zone": "saas", "label": "SaaS", "hint": "(fertig nutzen)" }
      ],
      "sortCards": [
        { "id": "p1", "text": "Du brauchst eine VM mit eigenem OS, spezieller Konfiguration und eigenem Patch-Plan", "correctZone": "iaas" },
        { "id": "p2", "text": "Du willst eine Web-App deployen, ohne OS zu pflegen; Runtime/DB soll gemanaged sein", "correctZone": "paas" },
        { "id": "p3", "text": "Du willst sofort ein Ticket-/CRM-System nutzen, ohne Installation/Serverbetrieb", "correctZone": "saas" },
        { "id": "p4", "text": "Du möchtest maximale Freiheit bei Netzwerk/Storage/VM-Größen", "correctZone": "iaas" },
        { "id": "p5", "text": "Du akzeptierst weniger Kontrolle zugunsten von weniger Betriebsaufwand", "correctZone": "paas" }
      ]
    }
  ]
}
